setup.cfg
setup.py
CsuTracking.egg-info/PKG-INFO
CsuTracking.egg-info/SOURCES.txt
CsuTracking.egg-info/dependency_links.txt
CsuTracking.egg-info/requires.txt
CsuTracking.egg-info/top_level.txt
Tracking/__init__.py
Tracking/convert.py
Tracking/model.py
Tracking/yolo.py
Tracking/deep_sort/__init__.py
Tracking/deep_sort/detection.py
Tracking/deep_sort/iou_matching.py
Tracking/deep_sort/kalman_filter.py
Tracking/deep_sort/linear_assignment.py
Tracking/deep_sort/nn_matching.py
Tracking/deep_sort/preprocessing.py
Tracking/deep_sort/track.py
Tracking/deep_sort/tracker.py
Tracking/tools/__init__.py
Tracking/tools/freeze_model.py
Tracking/tools/generate_detections.py
Tracking/yolo3/__init__.py
Tracking/yolo3/model.py
Tracking/yolo3/utils.py