Metadata-Version: 1.0
Name: CsuTracking
Version: 2.0.34
Summary: person or car
Home-page: UNKNOWN
Author: csu_ywj
Author-email: UNKNOWN
License: MIT Licence
Keywords: pip,Tracking
Platform: any
